pypsha/__init__.py
pypsha/find_modules.py
pypsha/psha.py
pypsha/utils.py
pypsha/jars/IM_EventSetCalc_v3_0_ASCII.jar
pypsha-0.0.3.dist-info/METADATA
pypsha-0.0.3.dist-info/WHEEL
pypsha-0.0.3.dist-info/top_level.txt
pypsha-0.0.3.dist-info/RECORD
